blaster/__init__.py
blur/__init__.py
blur/modeling/__init__.py
blur/modeling/blur.py
blur/modeling/decoders/__init__.py
blur/modeling/decoders/decoder.py
blur/modeling/decoders/decoderxl.py
blur/modeling/initializers/__init__.py
blur/modeling/initializers/xl.py
blur/modeling/modules/__init__.py
blur/modeling/modules/adaptive/__init__.py
blur/modeling/modules/adaptive/adaptive.py
blur/modeling/modules/attention/__init__.py
blur/modeling/modules/attention/base.py
blur/modeling/modules/attention/rel.py
blur/modeling/modules/dense/__init__.py
blur/modeling/modules/dense/positionwise.py
blur/modeling/modules/embedding/__init__.py
blur/modeling/modules/embedding/positional.py
blur/processing/__init__.py
blur/processing/corpus.py
blur/processing/vocabulary.py
blur/training/__init__.py
blur/training/exp_utils.py
blur/training/optimizer.py
blur/training/stream_dataset.py
blur/training/trainer.py
blur/utils/__init__.py
blur/utils/config.py
perceptor/__init__.py
devastator-0.1.2.dist-info/METADATA
devastator-0.1.2.dist-info/WHEEL
devastator-0.1.2.dist-info/top_level.txt
devastator-0.1.2.dist-info/RECORD
