Metadata-Version: 2.1
Name: devastator
Version: 0.1.2
Summary: UNKNOWN
Home-page: UNKNOWN
Author: UNKNOWN
Author-email: UNKNOWN
License: UNKNOWN
Platform: UNKNOWN
Requires-Dist: numpy
Requires-Dist: tqdm
Requires-Dist: torch
